chia_tea/__init__.py
chia_tea/cli/__init__.py
chia_tea/cli/config.py
chia_tea/cli/main.py
chia_tea/cli/start.py
chia_tea/cli/test_config.py
chia_tea/cli/test_start.py
chia_tea/copy/Disk.py
chia_tea/copy/Lockfile.py
chia_tea/copy/__init__.py
chia_tea/copy/main.py
chia_tea/discord/__init__.py
chia_tea/discord/bot.py
chia_tea/discord/commands/__init__.py
chia_tea/discord/commands/farmers.py
chia_tea/discord/commands/harvesters.py
chia_tea/discord/commands/machines.py
chia_tea/discord/commands/plotters.py
chia_tea/discord/commands/sql.py
chia_tea/discord/commands/test_farmers.py
chia_tea/discord/commands/test_harvesters.py
chia_tea/discord/commands/test_machines.py
chia_tea/discord/commands/test_plotters.py
chia_tea/discord/commands/test_sql.py
chia_tea/discord/commands/test_wallets.py
chia_tea/discord/commands/wallets.py
chia_tea/discord/common.py
chia_tea/discord/formatting.py
chia_tea/discord/notifications/__init__.py
chia_tea/discord/notifications/computer_info_notifications.py
chia_tea/discord/notifications/run_notifiers.py
chia_tea/discord/notifications/test_computer_info_notifications.py
chia_tea/discord/notifications/test_run_notifiers.py
chia_tea/discord/notifications/test_update_event_notifications.py
chia_tea/discord/notifications/update_event_notifications.py
chia_tea/discord/test_formatting.py
chia_tea/general/AbstractLineAction.py
chia_tea/general/__init__.py
chia_tea/general/file_watching.py
chia_tea/general/test_file_watching.py
chia_tea/models/ChiaWatchdog.py
chia_tea/models/FarmerAPI.py
chia_tea/models/FarmerHarvesterAPI.py
chia_tea/models/FarmerHarvesterLogfile.py
chia_tea/models/HarvesterAPI.py
chia_tea/models/MadMaxPlotInProgress.py
chia_tea/models/WalletAPI.py
chia_tea/models/__init__.py
chia_tea/models/test_ChiaWatchdog.py
chia_tea/monitoring/MonitoringClient.py
chia_tea/monitoring/MonitoringDatabase.py
chia_tea/monitoring/MonitoringServer.py
chia_tea/monitoring/__init__.py
chia_tea/monitoring/common.py
chia_tea-0.3.0.dist-info/entry_points.txt
chia_tea-0.3.0.dist-info/LICENSE
chia_tea-0.3.0.dist-info/WHEEL
chia_tea-0.3.0.dist-info/METADATA
chia_tea-0.3.0.dist-info/RECORD
