Metadata-Version: 2.1
Name: chia-tea
Version: 0.3.0
Summary: A library dedicated to chia-blockchain farmer.
Home-page: https://www.youtube.com/channel/UCba194Pls_bHSqWoWMGoyzA
License: BSD-3
Author: Tea n Tech
Requires-Python: >=3.7,<4.0
Classifier: Development Status :: 3 - Alpha
Classifier: Environment :: Console
Classifier: Intended Audience :: Developers
Classifier: Intended Audience :: Information Technology
Classifier: Intended Audience :: System Administrators
Classifier: License :: OSI Approved :: BSD License
Classifier: License :: Other/Proprietary License
Classifier: Natural Language :: English
Classifier: Operating System :: Microsoft :: Windows
Classifier: Operating System :: POSIX
Classifier: Programming Language :: PL/SQL
Classifier: Programming Language :: Python :: 3
Classifier: Programming Language :: Python :: 3.10
Classifier: Programming Language :: Python :: 3.7
Classifier: Programming Language :: Python :: 3.8
Classifier: Programming Language :: Python :: 3.9
Classifier: Topic :: Communications :: Chat
Classifier: Topic :: Database
Classifier: Topic :: Scientific/Engineering
Classifier: Topic :: System :: Monitoring
Requires-Dist: PyYAML (>=5.4.1,<6.0.0)
Requires-Dist: aiohttp (==3.7.4)
Requires-Dist: chia-blockchain (>=1.2.10,<2.0.0)
Requires-Dist: concurrent-log-handler (>=0.9.19,<0.10.0)
Requires-Dist: discord (>=1.7.3,<2.0.0)
Requires-Dist: grpcio (>=1.39.0,<2.0.0)
Requires-Dist: protobuf (>=3.19.1,<4.0.0)
Requires-Dist: psutil (>=5.8.0,<6.0.0)
Requires-Dist: py-cpuinfo (>=8.0.0,<9.0.0)
Requires-Dist: pywin32 (==300); sys_platform == "win32"
Requires-Dist: rich (>=10.10.0,<11.0.0)
Requires-Dist: sortedcontainers (>=2.4.0,<3.0.0)
Requires-Dist: typer[all] (>=0.4.0,<0.5.0)
Project-URL: Repository, https://www.youtube.com/channel/UCba194Pls_bHSqWoWMGoyzA
